random_cli.py
random_cli-1.0.1.dist-info/entry_points.txt
random_cli-1.0.1.dist-info/LICENSE.md
random_cli-1.0.1.dist-info/WHEEL
random_cli-1.0.1.dist-info/METADATA
random_cli-1.0.1.dist-info/RECORD
