Metadata-Version: 1.2
Name: random_cli
Version: 1.0.1
Summary: a cli app that simply generates a random 64 character alphanumeric string.
Home-page: https://github.com/sunnz/random-cli.py
License: ISC
Author: Sunny Yiu
Author-email: sun@yiu.co
Requires-Python: ~=3.6
Classifier: License :: OSI Approved :: ISC License (ISCL)
Classifier: Development Status :: 5 - Production/Stable
Classifier: Topic :: Security
Classifier: Programming Language :: Python :: 3.6
Classifier: Programming Language :: Python :: 3.7
Requires-Dist: Click (>=5,<7)
